Memoria_RAM/Probador.v
module Probador(
	output reg [9:0] data_a,
	output reg [2:0] addr_wa, addr_ra,
	output reg we_a, re_a, clk,
	output reg [3:0] state,
	input [9:0] q_a
	);
	
	initial begin
		$dumpfile("Memoria_RAM.vcd");
		$dumpvars;      
		
		data_a <= 'b0;
		addr_wa <= 'b0;
		addr_ra <= 'b0;
		we_a <= 1;
		re_a <= 'b0;
		state <= 'b0;
	
        @(posedge clk);
		we_a <= 1;
		re_a <= 0;
		data_a <= 1111111111;

		@(posedge clk);
		addr_wa <= addr_wa+1;
		we_a <= 1;
		re_a <= 0;
		data_a <= 1010101010;
		
		@(posedge clk);
		addr_wa <= addr_wa+1;
		we_a <= 1;
		re_a <= 0;
		data_a <= 0101010101;


		@(posedge clk);
		addr_wa <= addr_wa+1;
		we_a <= 1;
		re_a <= 0;
		data_a <= 1111100000;

		@(posedge clk);
		re_a <= 1;
		we_a <= 0;
		
		@(posedge clk);
		addr_ra <= addr_ra+1;
		re_a <= 1;
		we_a <= 0;

		@(posedge clk);
		addr_ra <= addr_ra+1;
		re_a <= 1;
		we_a <= 0;

		@(posedge clk);
		addr_ra <= addr_ra+1;
		re_a <= 1;
		we_a <= 0;

		@(posedge clk);
		addr_wa <= addr_wa+1;
		we_a <= 1;
		re_a <= 0;
		data_a <= 0000000001;

		@(posedge clk);
		addr_wa <= addr_wa+1;
		we_a <= 1;
		re_a <= 0;
		data_a <= 0000000010;

		@(posedge clk);
		addr_wa <= addr_wa+1;
		we_a <= 1;
		re_a <= 0;
		data_a <= 0000000100;

		$finish;
	end
	
	// Reloj
	initial	clk	<= 0;			// Valor inicial al reloj, sino siempre será indeterminado
	always  #1 clk 	<= ~clk;		// Hace "toggle" cada 4 segundos

	
endmodule

Memoria_RAM/true_dpram_sclk.v
// Verilog HDL True Dual-Port RAM with Single Clock by Intel
// https://www.intel.com/content/www/us/en/support/programmable/support-resources/design-examples/horizontal/ver-true-dual-port-ram-sclk.html
// Utilizado y modificado con fines educativos

module true_dpram_sclk
(
	input [9:0] data_a,
	input [2:0] addr_wa, addr_ra,
	input we_a, re_a, clk,
	input [3:0] state,
	output reg [9:0] q_a
);
	// Declare the RAM variable
	reg [9:0] ram[7:0];
	
	always @ (posedge clk)
	begin
		if(state == 4'b0001)begin
        	q_a <= 0;
			ram[0] <= 0;
			ram[1] <= 0;
			ram[2] <= 0;
			ram[3] <= 0;
			ram[4] <= 0;
			ram[5] <= 0;
			ram[6] <= 0;
			ram[7] <= 0;
    	end
		else begin
			if (we_a) 
			begin
				ram[addr_wa] <= data_a;
			end
			if (re_a) 
			begin
				q_a <= ram[addr_ra];
			end
			else
			begin
				q_a <= 10'b0;
			end
		end
	end

endmodule

Memoria_RAM/Banco_pruebas.v
`timescale 	1s				/ 100ps
`include "true_dpram_sclk.v"
`include "Probador.v"

module Banco_pruebas;
	wire [9:0] data_a, q_a;
    wire [2:0] addr_wa, addr_ra;
	wire we_a, re_a, clk;
	wire [3:0] state;

	true_dpram_sclk Memoria_RAM_Conductual( /*AUTOINST*/
					       // Outputs
					       .q_a		(q_a[9:0]),
					       // Inputs
					       .data_a		(data_a[9:0]),
					       .addr_wa		(addr_wa[2:0]),
					       .addr_ra		(addr_ra[2:0]),
					       .we_a		(we_a),
					       .re_a		(re_a),
					       .clk		(clk),
					       .state		(state[3:0]));
						     
	Probador Probador( /*AUTOINST*/
			  // Outputs
			  .data_a		(data_a[9:0]),
			  .addr_wa		(addr_wa[2:0]),
			  .addr_ra		(addr_ra[2:0]),
			  .we_a			(we_a),
			  .re_a			(re_a),
			  .clk			(clk),
			  .state		(state[3:0]),
			  // Inputs
			  .q_a			(q_a[9:0]));

endmodule

Memoria_RAM/Memoria_RAM.vcd
$date
	Sat Nov  6 16:35:27 2021
$end
$version
	Icarus Verilog
$end
$timescale
	100ps
$end
$scope module Banco_pruebas $end
$var wire 1 ! we_a $end
$var wire 4 " state [3:0] $end
$var wire 1 # re_a $end
$var wire 10 $ q_a [9:0] $end
$var wire 10 % data_a [9:0] $end
$var wire 1 & clk $end
$var wire 3 ' addr_wa [2:0] $end
$var wire 3 ( addr_ra [2:0] $end
$scope module Memoria_RAM_Conductual $end
$var wire 1 ! we_a $end
$var wire 4 ) state [3:0] $end
$var wire 1 # re_a $end
$var wire 10 * data_a [9:0] $end
$var wire 1 & clk $end
$var wire 3 + addr_wa [2:0] $end
$var wire 3 , addr_ra [2:0] $end
$var reg 10 - q_a [9:0] $end
$upscope $end
$scope module Probador $end
$var wire 10 . q_a [9:0] $end
$var reg 3 / addr_ra [2:0] $end
$var reg 3 0 addr_wa [2:0] $end
$var reg 1 & clk $end
$var reg 10 1 data_a [9:0] $end
$var reg 1 # re_a $end
$var reg 4 2 state [3:0] $end
$var reg 1 ! we_a $end
$upscope $end
$upscope $end
$enddefinitions $end
#0
$dumpvars
b0 2
b0 1
b0 0
b0 /
bx .
bx -
b0 ,
b0 +
b0 *
b0 )
b0 (
b0 '
0&
b0 %
bx $
0#
b0 "
1!
$end
#10000000000
b0 $
b0 -
b0 .
b111000111 %
b111000111 *
b111000111 1
1&
#20000000000
0&
#30000000000
b1100010010 %
b1100010010 *
b1100010010 1
b1 '
b1 +
b1 0
1&
#40000000000
0&
#50000000000
b1010110101 %
b1010110101 *
b1010110101 1
b10 '
b10 +
b10 0
1&
#60000000000
0&
#70000000000
b1001100000 %
b1001100000 *
b1001100000 1
b11 '
b11 +
b11 0
1&
#80000000000
0&
#90000000000
0!
1#
1&
#100000000000
0&
#110000000000
b1 (
b1 ,
b1 /
b111000111 $
b111000111 -
b111000111 .
1&
#120000000000
0&
#130000000000
b1100010010 $
b1100010010 -
b1100010010 .
b10 (
b10 ,
b10 /
1&
#140000000000
0&
#150000000000
b11 (
b11 ,
b11 /
b1010110101 $
b1010110101 -
b1010110101 .
1&
